{
  "event_id": "mem_4_1774623897",
  "timestamp": "2026-03-27T08:04:57",
  "task_id": "writing_word_wrap",
  "phase": "planning",
  "query": "Wrap this text at 20 characters per line without breaking words",
  "retrieved": [
    "Procedure for: Remove duplicate words from this text preserving order"
  ],
  "decision_before": "plan_from_scratch",
  "decision_after": "use_skill:skill_writing_remove_duplicates_1774623897",
  "decision_changed": true,
  "outcome": "success",
  "outcome_improved": true
}