{
  "event_id": "mem_41_1774623897",
  "timestamp": "2026-03-27T08:04:57",
  "task_id": "ops_memory_parse",
  "phase": "planning",
  "query": "Parse this memory info and return total, used, and free in GB",
  "retrieved": [
    "Procedure for: Parse this memory info and return total, used, and free in G"
  ],
  "decision_before": "plan_from_scratch",
  "decision_after": "use_skill:skill_ops_memory_parse_1774511676",
  "decision_changed": true,
  "outcome": "success",
  "outcome_improved": true
}